presidentsCTF/__init__.py
presidentsCTF/api.py
presidentsCTF/config.py
presidentsCTF/db.py
presidentsCTF/display.py
presidentsCTF/main.py
presidentsCTF/notify.py
presidentsCTF/stats.py
presidentsCTF_bot-0.0.6.dist-info/LICENSE
presidentsCTF_bot-0.0.6.dist-info/METADATA
presidentsCTF_bot-0.0.6.dist-info/WHEEL
presidentsCTF_bot-0.0.6.dist-info/entry_points.txt
presidentsCTF_bot-0.0.6.dist-info/top_level.txt
presidentsCTF_bot-0.0.6.dist-info/RECORD
