Metadata-Version: 2.1
Name: presidentsCTF-bot
Version: 0.0.6
Summary: Local scoreboard and bot to track the President's Cup.
Home-page: https://gitlab.com/royragsdale/presidentsctf-bot
Author: Roy Ragsdale
License: UNKNOWN
Project-URL: Bug Reports, https://gitlab.com/royragsdale/presidentsctf-bot/issues
Project-URL: Source, https://gitlab.com/royragsdale/presidentsctf-bot/
Platform: UNKNOWN
Classifier: Programming Language :: Python :: 3
Classifier: License :: OSI Approved :: MIT License
Classifier: Operating System :: OS Independent
Requires-Python: >=3.6
Requires-Dist: tabulate
Requires-Dist: slackclient
Requires-Dist: tweepy
